recording_tool/__init__.py
recording_tool/__main__.py
recording_tool/backup
python_recording_tool-0.1.2.dist-info/METADATA
python_recording_tool-0.1.2.dist-info/WHEEL
python_recording_tool-0.1.2.dist-info/entry_points.txt
python_recording_tool-0.1.2.dist-info/RECORD
